{"nodes": [{"id": "fl_fedproto_fedprotoconfig", "label": "FedProtoConfig", "file_type": "code", "source_file": "src/fl/fedproto.py", "source_location": "fedproto.py:96", "source_url": null, "captured_at": null, "author": null, "contributor": null}, {"id": "fl_fedproto_local_train_with_proto", "label": "_local_train_with_proto", "file_type": "code", "source_file": "src/fl/fedproto.py", "source_location": "fedproto.py:122", "source_url": null, "captured_at": null, "author": null, "contributor": null}, {"id": "fl_fedproto_local_h_g_centroids", "label": "_local_h_g_centroids", "file_type": "code", "source_file": "src/fl/fedproto.py", "source_location": "fedproto.py:179", "source_url": null, "captured_at": null, "author": null, "contributor": null}, {"id": "fl_fedproto_aggregate_prototypes", "label": "_aggregate_prototypes", "file_type": "code", "source_file": "src/fl/fedproto.py", "source_location": "fedproto.py:223", "source_url": null, "captured_at": null, "author": null, "contributor": null}, {"id": "fl_fedproto_initial_prototypes_from_clients", "label": "_initial_prototypes_from_clients", "file_type": "code", "source_file": "src/fl/fedproto.py", "source_location": "fedproto.py:267", "source_url": null, "captured_at": null, "author": null, "contributor": null}, {"id": "fl_fedproto_train_fedproto", "label": "train_fedproto", "file_type": "code", "source_file": "src/fl/fedproto.py", "source_location": "fedproto.py:298", "source_url": null, "captured_at": null, "author": null, "contributor": null}, {"id": "concept_fedproto_prototypes", "label": "FedProto per-cluster prototypes on h_g latents", "file_type": "concept", "source_file": "src/fl/fedproto.py", "source_location": null, "source_url": null, "captured_at": null, "author": null, "contributor": null}], "edges": [{"source": "fl_fedproto_train_fedproto", "target": "fl_base_build_clients", "relation": "calls", "confidence": "EXTRACTED", "confidence_score": 1.0, "source_file": "src/fl/fedproto.py", "source_location": "fedproto.py:310", "weight": 1.0}, {"source": "fl_fedproto_train_fedproto", "target": "fl_base_init_backbone", "relation": "calls", "confidence": "EXTRACTED", "confidence_score": 1.0, "source_file": "src/fl/fedproto.py", "source_location": "fedproto.py:315", "weight": 1.0}, {"source": "fl_fedproto_train_fedproto", "target": "fl_fedproto_initial_prototypes_from_clients", "relation": "calls", "confidence": "EXTRACTED", "confidence_score": 1.0, "source_file": "src/fl/fedproto.py", "source_location": "fedproto.py:321", "weight": 1.0}, {"source": "fl_fedproto_train_fedproto", "target": "fl_fedproto_local_train_with_proto", "relation": "calls", "confidence": "EXTRACTED", "confidence_score": 1.0, "source_file": "src/fl/fedproto.py", "source_location": "fedproto.py:355", "weight": 1.0}, {"source": "fl_fedproto_train_fedproto", "target": "fl_fedproto_local_h_g_centroids", "relation": "calls", "confidence": "EXTRACTED", "confidence_score": 1.0, "source_file": "src/fl/fedproto.py", "source_location": "fedproto.py:364", "weight": 1.0}, {"source": "fl_fedproto_train_fedproto", "target": "fl_fedproto_aggregate_prototypes", "relation": "calls", "confidence": "EXTRACTED", "confidence_score": 1.0, "source_file": "src/fl/fedproto.py", "source_location": "fedproto.py:381", "weight": 1.0}, {"source": "fl_fedproto_train_fedproto", "target": "fl_base_weighted_average", "relation": "calls", "confidence": "EXTRACTED", "confidence_score": 1.0, "source_file": "src/fl/fedproto.py", "source_location": "fedproto.py:379", "weight": 1.0}, {"source": "fl_fedproto_train_fedproto", "target": "fl_base_evaluate_cold", "relation": "calls", "confidence": "EXTRACTED", "confidence_score": 1.0, "source_file": "src/fl/fedproto.py", "source_location": "fedproto.py:396", "weight": 1.0}, {"source": "fl_fedproto_train_fedproto", "target": "concept_fedproto_prototypes", "relation": "implements", "confidence": "EXTRACTED", "confidence_score": 1.0, "source_file": "src/fl/fedproto.py", "source_location": null, "weight": 1.0}, {"source": "fl_fedproto_fedprotoconfig", "target": "fl_base_flconfig", "relation": "implements", "confidence": "EXTRACTED", "confidence_score": 1.0, "source_file": "src/fl/fedproto.py", "source_location": "fedproto.py:96", "weight": 1.0}], "hyperedges": []}