{"nodes": [{"id": "c_users_home_jw_research_docs_fl_peak_project_papers_literlature_fedprox_official_fedbase_py", "label": "fedbase.py", "file_type": "code", "source_file": "C:\\Users\\HOME\\JW\\Research Docs\\FL_Peak_Project\\papers\\literlature\\fedprox_official\\fedbase.py", "source_location": "L1"}, {"id": "fedprox_official_fedbase_basefedarated", "label": "BaseFedarated", "file_type": "code", "source_file": "C:\\Users\\HOME\\JW\\Research Docs\\FL_Peak_Project\\papers\\literlature\\fedprox_official\\fedbase.py", "source_location": "L9"}, {"id": "object", "label": "object", "file_type": "code", "source_file": "", "source_location": ""}, {"id": "fedprox_official_fedbase_basefedarated_init", "label": ".__init__()", "file_type": "code", "source_file": "C:\\Users\\HOME\\JW\\Research Docs\\FL_Peak_Project\\papers\\literlature\\fedprox_official\\fedbase.py", "source_location": "L10"}, {"id": "fedprox_official_fedbase_basefedarated_del", "label": ".__del__()", "file_type": "code", "source_file": "C:\\Users\\HOME\\JW\\Research Docs\\FL_Peak_Project\\papers\\literlature\\fedprox_official\\fedbase.py", "source_location": "L24"}, {"id": "fedprox_official_fedbase_basefedarated_setup_clients", "label": ".setup_clients()", "file_type": "code", "source_file": "C:\\Users\\HOME\\JW\\Research Docs\\FL_Peak_Project\\papers\\literlature\\fedprox_official\\fedbase.py", "source_location": "L27"}, {"id": "fedprox_official_fedbase_basefedarated_train_error_and_loss", "label": ".train_error_and_loss()", "file_type": "code", "source_file": "C:\\Users\\HOME\\JW\\Research Docs\\FL_Peak_Project\\papers\\literlature\\fedprox_official\\fedbase.py", "source_location": "L39"}, {"id": "fedprox_official_fedbase_basefedarated_show_grads", "label": ".show_grads()", "file_type": "code", "source_file": "C:\\Users\\HOME\\JW\\Research Docs\\FL_Peak_Project\\papers\\literlature\\fedprox_official\\fedbase.py", "source_location": "L56"}, {"id": "fedprox_official_fedbase_basefedarated_test", "label": ".test()", "file_type": "code", "source_file": "C:\\Users\\HOME\\JW\\Research Docs\\FL_Peak_Project\\papers\\literlature\\fedprox_official\\fedbase.py", "source_location": "L81"}, {"id": "fedprox_official_fedbase_basefedarated_save", "label": ".save()", "file_type": "code", "source_file": "C:\\Users\\HOME\\JW\\Research Docs\\FL_Peak_Project\\papers\\literlature\\fedprox_official\\fedbase.py", "source_location": "L95"}, {"id": "fedprox_official_fedbase_basefedarated_select_clients", "label": ".select_clients()", "file_type": "code", "source_file": "C:\\Users\\HOME\\JW\\Research Docs\\FL_Peak_Project\\papers\\literlature\\fedprox_official\\fedbase.py", "source_location": "L98"}, {"id": "fedprox_official_fedbase_basefedarated_aggregate", "label": ".aggregate()", "file_type": "code", "source_file": "C:\\Users\\HOME\\JW\\Research Docs\\FL_Peak_Project\\papers\\literlature\\fedprox_official\\fedbase.py", "source_location": "L115"}, {"id": "fedprox_official_fedbase_rationale_28", "label": "instantiates clients based on given train and test data directories          R", "file_type": "rationale", "source_file": "C:\\Users\\HOME\\JW\\Research Docs\\FL_Peak_Project\\papers\\literlature\\fedprox_official\\fedbase.py", "source_location": "L28"}, {"id": "fedprox_official_fedbase_rationale_57", "label": "Return:             gradients on all workers and the global gradient", "file_type": "rationale", "source_file": "C:\\Users\\HOME\\JW\\Research Docs\\FL_Peak_Project\\papers\\literlature\\fedprox_official\\fedbase.py", "source_location": "L57"}, {"id": "fedprox_official_fedbase_rationale_82", "label": "tests self.latest_model on given clients", "file_type": "rationale", "source_file": "C:\\Users\\HOME\\JW\\Research Docs\\FL_Peak_Project\\papers\\literlature\\fedprox_official\\fedbase.py", "source_location": "L82"}, {"id": "fedprox_official_fedbase_rationale_99", "label": "selects num_clients clients weighted by number of samples from possible_clients", "file_type": "rationale", "source_file": "C:\\Users\\HOME\\JW\\Research Docs\\FL_Peak_Project\\papers\\literlature\\fedprox_official\\fedbase.py", "source_location": "L99"}], "edges": [{"source": "c_users_home_jw_research_docs_fl_peak_project_papers_literlature_fedprox_official_fedbase_py", "target": "numpy", "relation": "imports", "context": "import", "confidence": "EXTRACTED", "source_file": "C:\\Users\\HOME\\JW\\Research Docs\\FL_Peak_Project\\papers\\literlature\\fedprox_official\\fedbase.py", "source_location": "L1", "weight": 1.0}, {"source": "c_users_home_jw_research_docs_fl_peak_project_papers_literlature_fedprox_official_fedbase_py", "target": "tensorflow", "relation": "imports", "context": "import", "confidence": "EXTRACTED", "source_file": "C:\\Users\\HOME\\JW\\Research Docs\\FL_Peak_Project\\papers\\literlature\\fedprox_official\\fedbase.py", "source_location": "L2", "weight": 1.0}, {"source": "c_users_home_jw_research_docs_fl_peak_project_papers_literlature_fedprox_official_fedbase_py", "target": "tqdm", "relation": "imports_from", "context": "import", "confidence": "EXTRACTED", "source_file": "C:\\Users\\HOME\\JW\\Research Docs\\FL_Peak_Project\\papers\\literlature\\fedprox_official\\fedbase.py", "source_location": "L3", "weight": 1.0}, {"source": "c_users_home_jw_research_docs_fl_peak_project_papers_literlature_fedprox_official_fedbase_py", "target": "flearn_models_client", "relation": "imports_from", "context": "import", "confidence": "EXTRACTED", "source_file": "C:\\Users\\HOME\\JW\\Research Docs\\FL_Peak_Project\\papers\\literlature\\fedprox_official\\fedbase.py", "source_location": "L5", "weight": 1.0}, {"source": "c_users_home_jw_research_docs_fl_peak_project_papers_literlature_fedprox_official_fedbase_py", "target": "flearn_utils_model_utils", "relation": "imports_from", "context": "import", "confidence": "EXTRACTED", "source_file": "C:\\Users\\HOME\\JW\\Research Docs\\FL_Peak_Project\\papers\\literlature\\fedprox_official\\fedbase.py", "source_location": "L6", "weight": 1.0}, {"source": "c_users_home_jw_research_docs_fl_peak_project_papers_literlature_fedprox_official_fedbase_py", "target": "flearn_utils_tf_utils", "relation": "imports_from", "context": "import", "confidence": "EXTRACTED", "source_file": "C:\\Users\\HOME\\JW\\Research Docs\\FL_Peak_Project\\papers\\literlature\\fedprox_official\\fedbase.py", "source_location": "L7", "weight": 1.0}, {"source": "c_users_home_jw_research_docs_fl_peak_project_papers_literlature_fedprox_official_fedbase_py", "target": "fedprox_official_fedbase_basefedarated", "relation": "contains", "confidence": "EXTRACTED", "source_file": "C:\\Users\\HOME\\JW\\Research Docs\\FL_Peak_Project\\papers\\literlature\\fedprox_official\\fedbase.py", "source_location": "L9", "weight": 1.0}, {"source": "fedprox_official_fedbase_basefedarated", "target": "object", "relation": "inherits", "confidence": "EXTRACTED", "source_file": "C:\\Users\\HOME\\JW\\Research Docs\\FL_Peak_Project\\papers\\literlature\\fedprox_official\\fedbase.py", "source_location": "L9", "weight": 1.0}, {"source": "fedprox_official_fedbase_basefedarated", "target": "fedprox_official_fedbase_basefedarated_init", "relation": "method", "confidence": "EXTRACTED", "source_file": "C:\\Users\\HOME\\JW\\Research Docs\\FL_Peak_Project\\papers\\literlature\\fedprox_official\\fedbase.py", "source_location": "L10", "weight": 1.0}, {"source": "fedprox_official_fedbase_basefedarated", "target": "fedprox_official_fedbase_basefedarated_del", "relation": "method", "confidence": "EXTRACTED", "source_file": "C:\\Users\\HOME\\JW\\Research Docs\\FL_Peak_Project\\papers\\literlature\\fedprox_official\\fedbase.py", "source_location": "L24", "weight": 1.0}, {"source": "fedprox_official_fedbase_basefedarated", "target": "fedprox_official_fedbase_basefedarated_setup_clients", "relation": "method", "confidence": "EXTRACTED", "source_file": "C:\\Users\\HOME\\JW\\Research Docs\\FL_Peak_Project\\papers\\literlature\\fedprox_official\\fedbase.py", "source_location": "L27", "weight": 1.0}, {"source": "fedprox_official_fedbase_basefedarated", "target": "fedprox_official_fedbase_basefedarated_train_error_and_loss", "relation": "method", "confidence": "EXTRACTED", "source_file": "C:\\Users\\HOME\\JW\\Research Docs\\FL_Peak_Project\\papers\\literlature\\fedprox_official\\fedbase.py", "source_location": "L39", "weight": 1.0}, {"source": "fedprox_official_fedbase_basefedarated", "target": "fedprox_official_fedbase_basefedarated_show_grads", "relation": "method", "confidence": "EXTRACTED", "source_file": "C:\\Users\\HOME\\JW\\Research Docs\\FL_Peak_Project\\papers\\literlature\\fedprox_official\\fedbase.py", "source_location": "L56", "weight": 1.0}, {"source": "fedprox_official_fedbase_basefedarated", "target": "fedprox_official_fedbase_basefedarated_test", "relation": "method", "confidence": "EXTRACTED", "source_file": "C:\\Users\\HOME\\JW\\Research Docs\\FL_Peak_Project\\papers\\literlature\\fedprox_official\\fedbase.py", "source_location": "L81", "weight": 1.0}, {"source": "fedprox_official_fedbase_basefedarated", "target": "fedprox_official_fedbase_basefedarated_save", "relation": "method", "confidence": "EXTRACTED", "source_file": "C:\\Users\\HOME\\JW\\Research Docs\\FL_Peak_Project\\papers\\literlature\\fedprox_official\\fedbase.py", "source_location": "L95", "weight": 1.0}, {"source": "fedprox_official_fedbase_basefedarated", "target": "fedprox_official_fedbase_basefedarated_select_clients", "relation": "method", "confidence": "EXTRACTED", "source_file": "C:\\Users\\HOME\\JW\\Research Docs\\FL_Peak_Project\\papers\\literlature\\fedprox_official\\fedbase.py", "source_location": "L98", "weight": 1.0}, {"source": "fedprox_official_fedbase_basefedarated", "target": "fedprox_official_fedbase_basefedarated_aggregate", "relation": "method", "confidence": "EXTRACTED", "source_file": "C:\\Users\\HOME\\JW\\Research Docs\\FL_Peak_Project\\papers\\literlature\\fedprox_official\\fedbase.py", "source_location": "L115", "weight": 1.0}, {"source": "fedprox_official_fedbase_basefedarated_init", "target": "fedprox_official_fedbase_basefedarated_setup_clients", "relation": "calls", "context": "call", "confidence": "EXTRACTED", "source_file": "C:\\Users\\HOME\\JW\\Research Docs\\FL_Peak_Project\\papers\\literlature\\fedprox_official\\fedbase.py", "source_location": "L17", "weight": 1.0}, {"source": "fedprox_official_fedbase_rationale_28", "target": "fedprox_official_fedbase_basefedarated_setup_clients", "relation": "rationale_for", "confidence": "EXTRACTED", "source_file": "C:\\Users\\HOME\\JW\\Research Docs\\FL_Peak_Project\\papers\\literlature\\fedprox_official\\fedbase.py", "source_location": "L28", "weight": 1.0}, {"source": "fedprox_official_fedbase_rationale_57", "target": "fedprox_official_fedbase_basefedarated_show_grads", "relation": "rationale_for", "confidence": "EXTRACTED", "source_file": "C:\\Users\\HOME\\JW\\Research Docs\\FL_Peak_Project\\papers\\literlature\\fedprox_official\\fedbase.py", "source_location": "L57", "weight": 1.0}, {"source": "fedprox_official_fedbase_rationale_82", "target": "fedprox_official_fedbase_basefedarated_test", "relation": "rationale_for", "confidence": "EXTRACTED", "source_file": "C:\\Users\\HOME\\JW\\Research Docs\\FL_Peak_Project\\papers\\literlature\\fedprox_official\\fedbase.py", "source_location": "L82", "weight": 1.0}, {"source": "fedprox_official_fedbase_rationale_99", "target": "fedprox_official_fedbase_basefedarated_select_clients", "relation": "rationale_for", "confidence": "EXTRACTED", "source_file": "C:\\Users\\HOME\\JW\\Research Docs\\FL_Peak_Project\\papers\\literlature\\fedprox_official\\fedbase.py", "source_location": "L99", "weight": 1.0}], "raw_calls": [{"caller_nid": "fedprox_official_fedbase_basefedarated_init", "callee": "items", "is_member_call": true, "source_file": "C:\\Users\\HOME\\JW\\Research Docs\\FL_Peak_Project\\papers\\literlature\\fedprox_official\\fedbase.py", "source_location": "L12"}, {"caller_nid": "fedprox_official_fedbase_basefedarated_init", "callee": "setattr", "is_member_call": false, "source_file": "C:\\Users\\HOME\\JW\\Research Docs\\FL_Peak_Project\\papers\\literlature\\fedprox_official\\fedbase.py", "source_location": "L12"}, {"caller_nid": "fedprox_official_fedbase_basefedarated_init", "callee": "reset_default_graph", "is_member_call": true, "source_file": "C:\\Users\\HOME\\JW\\Research Docs\\FL_Peak_Project\\papers\\literlature\\fedprox_official\\fedbase.py", "source_location": "L15"}, {"caller_nid": "fedprox_official_fedbase_basefedarated_init", "callee": "learner", "is_member_call": false, "source_file": "C:\\Users\\HOME\\JW\\Research Docs\\FL_Peak_Project\\papers\\literlature\\fedprox_official\\fedbase.py", "source_location": "L16"}, {"caller_nid": "fedprox_official_fedbase_basefedarated_init", "callee": "print", "is_member_call": false, "source_file": "C:\\Users\\HOME\\JW\\Research Docs\\FL_Peak_Project\\papers\\literlature\\fedprox_official\\fedbase.py", "source_location": "L18"}, {"caller_nid": "fedprox_official_fedbase_basefedarated_init", "callee": "format", "is_member_call": true, "source_file": "C:\\Users\\HOME\\JW\\Research Docs\\FL_Peak_Project\\papers\\literlature\\fedprox_official\\fedbase.py", "source_location": "L18"}, {"caller_nid": "fedprox_official_fedbase_basefedarated_init", "callee": "len", "is_member_call": false, "source_file": "C:\\Users\\HOME\\JW\\Research Docs\\FL_Peak_Project\\papers\\literlature\\fedprox_official\\fedbase.py", "source_location": "L18"}, {"caller_nid": "fedprox_official_fedbase_basefedarated_init", "callee": "get_params", "is_member_call": true, "source_file": "C:\\Users\\HOME\\JW\\Research Docs\\FL_Peak_Project\\papers\\literlature\\fedprox_official\\fedbase.py", "source_location": "L19"}, {"caller_nid": "fedprox_official_fedbase_basefedarated_init", "callee": "Metrics", "is_member_call": false, "source_file": "C:\\Users\\HOME\\JW\\Research Docs\\FL_Peak_Project\\papers\\literlature\\fedprox_official\\fedbase.py", "source_location": "L22"}, {"caller_nid": "fedprox_official_fedbase_basefedarated_del", "callee": "close", "is_member_call": true, "source_file": "C:\\Users\\HOME\\JW\\Research Docs\\FL_Peak_Project\\papers\\literlature\\fedprox_official\\fedbase.py", "source_location": "L25"}, {"caller_nid": "fedprox_official_fedbase_basefedarated_setup_clients", "callee": "len", "is_member_call": false, "source_file": "C:\\Users\\HOME\\JW\\Research Docs\\FL_Peak_Project\\papers\\literlature\\fedprox_official\\fedbase.py", "source_location": "L34"}, {"caller_nid": "fedprox_official_fedbase_basefedarated_setup_clients", "callee": "Client", "is_member_call": false, "source_file": "C:\\Users\\HOME\\JW\\Research Docs\\FL_Peak_Project\\papers\\literlature\\fedprox_official\\fedbase.py", "source_location": "L36"}, {"caller_nid": "fedprox_official_fedbase_basefedarated_setup_clients", "callee": "zip", "is_member_call": false, "source_file": "C:\\Users\\HOME\\JW\\Research Docs\\FL_Peak_Project\\papers\\literlature\\fedprox_official\\fedbase.py", "source_location": "L36"}, {"caller_nid": "fedprox_official_fedbase_basefedarated_train_error_and_loss", "callee": "append", "is_member_call": true, "source_file": "C:\\Users\\HOME\\JW\\Research Docs\\FL_Peak_Project\\papers\\literlature\\fedprox_official\\fedbase.py", "source_location": "L46"}, {"caller_nid": "fedprox_official_fedbase_basefedarated_train_error_and_loss", "callee": "append", "is_member_call": true, "source_file": "C:\\Users\\HOME\\JW\\Research Docs\\FL_Peak_Project\\papers\\literlature\\fedprox_official\\fedbase.py", "source_location": "L47"}, {"caller_nid": "fedprox_official_fedbase_basefedarated_train_error_and_loss", "callee": "append", "is_member_call": true, "source_file": "C:\\Users\\HOME\\JW\\Research Docs\\FL_Peak_Project\\papers\\literlature\\fedprox_official\\fedbase.py", "source_location": "L48"}, {"caller_nid": "fedprox_official_fedbase_basefedarated_show_grads", "callee": "process_grad", "is_member_call": false, "source_file": "C:\\Users\\HOME\\JW\\Research Docs\\FL_Peak_Project\\papers\\literlature\\fedprox_official\\fedbase.py", "source_location": "L62"}, {"caller_nid": "fedprox_official_fedbase_basefedarated_show_grads", "callee": "zeros", "is_member_call": true, "source_file": "C:\\Users\\HOME\\JW\\Research Docs\\FL_Peak_Project\\papers\\literlature\\fedprox_official\\fedbase.py", "source_location": "L63"}, {"caller_nid": "fedprox_official_fedbase_basefedarated_show_grads", "callee": "set_params", "is_member_call": true, "source_file": "C:\\Users\\HOME\\JW\\Research Docs\\FL_Peak_Project\\papers\\literlature\\fedprox_official\\fedbase.py", "source_location": "L68"}, {"caller_nid": "fedprox_official_fedbase_basefedarated_show_grads", "callee": "get_grads", "is_member_call": true, "source_file": "C:\\Users\\HOME\\JW\\Research Docs\\FL_Peak_Project\\papers\\literlature\\fedprox_official\\fedbase.py", "source_location": "L70"}, {"caller_nid": "fedprox_official_fedbase_basefedarated_show_grads", "callee": "append", "is_member_call": true, "source_file": "C:\\Users\\HOME\\JW\\Research Docs\\FL_Peak_Project\\papers\\literlature\\fedprox_official\\fedbase.py", "source_location": "L71"}, {"caller_nid": "fedprox_official_fedbase_basefedarated_show_grads", "callee": "add", "is_member_call": true, "source_file": "C:\\Users\\HOME\\JW\\Research Docs\\FL_Peak_Project\\papers\\literlature\\fedprox_official\\fedbase.py", "source_location": "L72"}, {"caller_nid": "fedprox_official_fedbase_basefedarated_show_grads", "callee": "append", "is_member_call": true, "source_file": "C:\\Users\\HOME\\JW\\Research Docs\\FL_Peak_Project\\papers\\literlature\\fedprox_official\\fedbase.py", "source_location": "L73"}, {"caller_nid": "fedprox_official_fedbase_basefedarated_show_grads", "callee": "sum", "is_member_call": true, "source_file": "C:\\Users\\HOME\\JW\\Research Docs\\FL_Peak_Project\\papers\\literlature\\fedprox_official\\fedbase.py", "source_location": "L75"}, {"caller_nid": "fedprox_official_fedbase_basefedarated_show_grads", "callee": "asarray", "is_member_call": true, "source_file": "C:\\Users\\HOME\\JW\\Research Docs\\FL_Peak_Project\\papers\\literlature\\fedprox_official\\fedbase.py", "source_location": "L75"}, {"caller_nid": "fedprox_official_fedbase_basefedarated_show_grads", "callee": "append", "is_member_call": true, "source_file": "C:\\Users\\HOME\\JW\\Research Docs\\FL_Peak_Project\\papers\\literlature\\fedprox_official\\fedbase.py", "source_location": "L76"}, {"caller_nid": "fedprox_official_fedbase_basefedarated_test", "callee": "set_params", "is_member_call": true, "source_file": "C:\\Users\\HOME\\JW\\Research Docs\\FL_Peak_Project\\papers\\literlature\\fedprox_official\\fedbase.py", "source_location": "L86"}, {"caller_nid": "fedprox_official_fedbase_basefedarated_test", "callee": "append", "is_member_call": true, "source_file": "C:\\Users\\HOME\\JW\\Research Docs\\FL_Peak_Project\\papers\\literlature\\fedprox_official\\fedbase.py", "source_location": "L89"}, {"caller_nid": "fedprox_official_fedbase_basefedarated_test", "callee": "append", "is_member_call": true, "source_file": "C:\\Users\\HOME\\JW\\Research Docs\\FL_Peak_Project\\papers\\literlature\\fedprox_official\\fedbase.py", "source_location": "L90"}, {"caller_nid": "fedprox_official_fedbase_basefedarated_select_clients", "callee": "min", "is_member_call": false, "source_file": "C:\\Users\\HOME\\JW\\Research Docs\\FL_Peak_Project\\papers\\literlature\\fedprox_official\\fedbase.py", "source_location": "L110"}, {"caller_nid": "fedprox_official_fedbase_basefedarated_select_clients", "callee": "len", "is_member_call": false, "source_file": "C:\\Users\\HOME\\JW\\Research Docs\\FL_Peak_Project\\papers\\literlature\\fedprox_official\\fedbase.py", "source_location": "L110"}, {"caller_nid": "fedprox_official_fedbase_basefedarated_select_clients", "callee": "seed", "is_member_call": true, "source_file": "C:\\Users\\HOME\\JW\\Research Docs\\FL_Peak_Project\\papers\\literlature\\fedprox_official\\fedbase.py", "source_location": "L111"}, {"caller_nid": "fedprox_official_fedbase_basefedarated_select_clients", "callee": "choice", "is_member_call": true, "source_file": "C:\\Users\\HOME\\JW\\Research Docs\\FL_Peak_Project\\papers\\literlature\\fedprox_official\\fedbase.py", "source_location": "L112"}, {"caller_nid": "fedprox_official_fedbase_basefedarated_select_clients", "callee": "range", "is_member_call": false, "source_file": "C:\\Users\\HOME\\JW\\Research Docs\\FL_Peak_Project\\papers\\literlature\\fedprox_official\\fedbase.py", "source_location": "L112"}, {"caller_nid": "fedprox_official_fedbase_basefedarated_select_clients", "callee": "len", "is_member_call": false, "source_file": "C:\\Users\\HOME\\JW\\Research Docs\\FL_Peak_Project\\papers\\literlature\\fedprox_official\\fedbase.py", "source_location": "L112"}, {"caller_nid": "fedprox_official_fedbase_basefedarated_select_clients", "callee": "asarray", "is_member_call": true, "source_file": "C:\\Users\\HOME\\JW\\Research Docs\\FL_Peak_Project\\papers\\literlature\\fedprox_official\\fedbase.py", "source_location": "L113"}, {"caller_nid": "fedprox_official_fedbase_basefedarated_aggregate", "callee": "len", "is_member_call": false, "source_file": "C:\\Users\\HOME\\JW\\Research Docs\\FL_Peak_Project\\papers\\literlature\\fedprox_official\\fedbase.py", "source_location": "L117"}, {"caller_nid": "fedprox_official_fedbase_basefedarated_aggregate", "callee": "enumerate", "is_member_call": false, "source_file": "C:\\Users\\HOME\\JW\\Research Docs\\FL_Peak_Project\\papers\\literlature\\fedprox_official\\fedbase.py", "source_location": "L120"}, {"caller_nid": "fedprox_official_fedbase_basefedarated_aggregate", "callee": "astype", "is_member_call": true, "source_file": "C:\\Users\\HOME\\JW\\Research Docs\\FL_Peak_Project\\papers\\literlature\\fedprox_official\\fedbase.py", "source_location": "L121"}]}